{"nodes": [{"id": "readme_remake_dpp", "label": "ReMake DPP Package", "file_type": "document", "source_file": "README.md", "source_location": null, "source_url": null, "captured_at": null, "author": "Anmol Kumar", "contributor": null}], "edges": [{"source": "readme_remake_dpp", "target": "contributing_guide", "relation": "references", "confidence": "EXTRACTED", "confidence_score": 1.0, "source_file": "README.md", "source_location": "Contributing section", "weight": 1.0}, {"source": "readme_remake_dpp", "target": "license_mit", "relation": "references", "confidence": "EXTRACTED", "confidence_score": 1.0, "source_file": "README.md", "source_location": "License section", "weight": 1.0}, {"source": "readme_remake_dpp", "target": "prd_dpp_bridge", "relation": "references", "confidence": "EXTRACTED", "confidence_score": 1.0, "source_file": "README.md", "source_location": "Package Layout", "weight": 1.0}, {"source": "readme_remake_dpp", "target": "concept_digital_product_passport", "relation": "conceptually_related_to", "confidence": "EXTRACTED", "confidence_score": 1.0, "source_file": "README.md", "source_location": "Description", "weight": 1.0}, {"source": "readme_remake_dpp", "target": "docs_intro", "relation": "references", "confidence": "INFERRED", "confidence_score": 0.85, "source_file": "README.md", "source_location": "Package Layout docs/", "weight": 1.0}, {"source": "readme_remake_dpp", "target": "docs_quickstart", "relation": "references", "confidence": "INFERRED", "confidence_score": 0.85, "source_file": "README.md", "source_location": "Package Layout docs/", "weight": 1.0}, {"source": "readme_remake_dpp", "target": "docs_concepts_gas", "relation": "references", "confidence": "INFERRED", "confidence_score": 0.85, "source_file": "README.md", "source_location": "Package Layout docs/", "weight": 1.0}, {"source": "readme_remake_dpp", "target": "isa95_mapping_yaml", "relation": "references", "confidence": "EXTRACTED", "confidence_score": 1.0, "source_file": "README.md", "source_location": "Package Layout", "weight": 1.0}, {"source": "readme_remake_dpp", "target": "eclass_mapping_yaml", "relation": "references", "confidence": "EXTRACTED", "confidence_score": 1.0, "source_file": "README.md", "source_location": "Package Layout", "weight": 1.0}], "hyperedges": []}